{
    "Controlador.TDA.ListaDinamica.ListaDinamica": {
        "cabezera": {
            "info": {
                "@class": "Modelo.Docente",
                "IdDocente": 1,
                "EspecialidadD": "n",
                "TitulacionD": "n",
                "AniosExperienciaD": 2,
                "DatosDocente": {
                    "IdP": 2,
                    "TipoDNI": "Cedula",
                    "NroDNIP": 1100000001,
                    "NombreP": "Mario",
                    "ApellidoP": "Zambrano",
                    "GeneroP": "Masculino",
                    "FechaNP": "01\/febrero\/2024",
                    "DireP": "f",
                    "TelefonoP": "0900000001",
                    "rolPersona": {
                        "IdRol": 2,
                        "NombreR": "Docente",
                        "DescripcionR": "Es un Docente"
                    },
                    "cuentaPersona": {
                        "IdCuenta": 1,
                        "CorreoC": "mario.zambrano@unl.edu.ec",
                        "ContraseniaC": 1100000001,
                        "EstadoC": "Activa"
                    }
                }
            }
        },
        "ultimo": {
            "@reference": "..\/cabezera"
        },
        "Longitud": 1
    }
}